_gridpy.cpython-38-darwin.so
libgridpy-java.dylib
gridpy/__init__.py
gridpy/loadflow.py
gridpy/network.py
gridpy/security_analysis.py
gridpy/sensitivity_analysis.py
gridpy/util.py
gridpy-0.5.0.dist-info/LICENSE
gridpy-0.5.0.dist-info/METADATA
gridpy-0.5.0.dist-info/WHEEL
gridpy-0.5.0.dist-info/top_level.txt
gridpy-0.5.0.dist-info/RECORD
